shalaby_cli_demo/__init__.py
shalaby_cli_demo/main.py
shalaby_cli_demo-0.1.0.dist-info/entry_points.txt
shalaby_cli_demo-0.1.0.dist-info/WHEEL
shalaby_cli_demo-0.1.0.dist-info/METADATA
shalaby_cli_demo-0.1.0.dist-info/RECORD
