Metadata-Version: 2.1
Name: shalaby-cli-demo
Version: 0.1.0
Summary: This is a demo cli app package
Author: Mohamed Shalaby
Author-email: mhdshalabystar@gmail.com
Requires-Python: >=3.8,<4.0
Classifier: Programming Language :: Python :: 3
Classifier: Programming Language :: Python :: 3.10
Classifier: Programming Language :: Python :: 3.8
Classifier: Programming Language :: Python :: 3.9
Requires-Dist: typer[all] (>=0.6.1,<0.7.0)
